MANIFEST.in
NOTICE
README.rst
setup.cfg
setup.py
config/__init__.py
config/urls.py
config/wsgi.py
config/settings/__init__.py
config/settings/base.py
mfl.egg-info/PKG-INFO
mfl.egg-info/SOURCES.txt
mfl.egg-info/dependency_links.txt
mfl.egg-info/top_level.txt
minion/__init__.py
minion/tests.py