Metadata-Version: 1.1
Name: mfl
Version: 2.0a1
Summary: Core APIs for the Kenyan Ministry of Health Master Facility List
Home-page: UNKNOWN
Author: Savannah Informatics Limitee Developers
Author-email: developers@savannahinformatics.com
License: MIT License
Platform: any
Classifier: Programming Language :: Python
Classifier: Programming Language :: Python :: 2.7
Classifier: Development Status :: 3 - Alpha
Classifier: Natural Language :: English
Classifier: Environment :: Web Environment
Classifier: Intended Audience :: Developers
Classifier: Intended Audience :: Healthcare Industry
Classifier: License :: OSI Approved :: MIT License
Classifier: Operating System :: POSIX :: Linux
Classifier: Framework :: Django :: 1.8
Classifier: Topic :: Internet :: WWW/HTTP :: Dynamic Content
Classifier: Topic :: Internet :: WWW/HTTP :: WSGI :: Application
